{
	"Name": "Yun / ユン",
	"Category": "GeneiJin Specials",
	"Tetsu Zankou (Jab)": {
		"Motion": "DPM + Jab",
		"Startup": "7",
		"Hit": "9",
		"Recovery": "8",
		"Block Advantage": "5",
		"Cancel": {
      "?": false,
      "??": false,
			"Super Art": true,
			"Special": false,
			"Self": false,
			"Normal/Chain": false,
			"Dash": false,
			"Superjump": false
		},
		"Parry": "H+L",
		"Throw Range": "-",
		"Damage": "13",
		"Stun": "0",
		"Meter Gain Opponent": "0"
	},
	"Tetsu Zankou (Strong)": {
		"Motion": "DPM + Strong",
		"Startup": "8",
		"Hit": "10",
		"Recovery": "10",
		"Block Advantage": "5",
		"Cancel": {
      "?": false,
      "??": false,
			"Super Art": true,
			"Special": false,
			"Self": false,
			"Normal/Chain": false,
			"Dash": false,
			"Superjump": false
		},
		"Parry": "H+L",
		"Throw Range": "-",
		"Damage": "17",
		"Stun": "0",
		"Meter Gain Opponent": "0"
	},
	"Tetsu Zankou (Fierce)": {
		"Motion": "DPM + Fierce",
		"Startup": "10",
		"Hit": "11",
		"Recovery": "12",
		"Block Advantage": "3",
		"Cancel": {
      "?": false,
      "??": false,
			"Super Art": true,
			"Special": false,
			"Self": false,
			"Normal/Chain": false,
			"Dash": false,
			"Superjump": false
		},
		"Parry": "H+L",
		"Throw Range": "-",
		"Damage": "17",
		"Stun": "0",
		"Meter Gain Opponent": "0"
	},
	"Zesshou Hohou": {
		"Motion": "QCF + Jab",
		"Startup": "7",
		"Hit": "15",
		"Recovery": "7",
		"Block Advantage": "-6",
		"Cancel": {
      "?": false,
      "??": false,
			"Super Art": false,
			"Special": false,
			"Self": false,
			"Normal/Chain": false,
			"Dash": false,
			"Superjump": false
		},
		"Parry": "H+L",
		"Throw Range": "-",
		"Damage": "16",
		"Stun": "0",
		"Meter Gain Opponent": "0"
	},
	"Nishou Kyaku (Short)": {
		"Motion": "DPM + Short",
		"Startup": "6",
		"Hit": "4",
		"Recovery": "20",
		"Block Advantage": "-11",
		"Cancel": {
      "?": false,
      "??": false,
			"Super Art": false,
			"Special": false,
			"Self": false,
			"Normal/Chain": false,
			"Dash": false,
			"Superjump": false
		},
		"Parry": "H+L",
		"Throw Range": "-",
		"Damage": "13",
		"Stun": "0",
		"Meter Gain Opponent": "0"
	},
	"Nishou Kyaku (Forward)": {
		"Motion": "DPM + Forward",
		"Startup": "6",
		"Hit": "4",
		"Recovery": "21",
		"Block Advantage": "-12",
		"Cancel": {
      "?": false,
      "??": false,
			"Super Art": false,
			"Special": false,
			"Self": false,
			"Normal/Chain": false,
			"Dash": false,
			"Superjump": false
		},
		"Parry": "H+L",
		"Throw Range": "-",
		"Damage": "13",
		"Stun": "0",
		"Meter Gain Opponent": "0"
	},
	"Nishou Kyaku (RH)": {
		"Motion": "DPM + Roundhouse",
		"Startup": "6",
		"Hit": "4",
		"Recovery": "22",
		"Block Advantage": "-13",
		"Cancel": {
      "?": false,
      "??": false,
			"Super Art": false,
			"Special": false,
			"Self": false,
			"Normal/Chain": false,
			"Dash": false,
			"Superjump": false
		},
		"Parry": "H+L",
		"Throw Range": "-",
		"Damage": "13",
		"Stun": "0",
		"Meter Gain Opponent": "0"
	},
	"Kobokushi": {
		"Motion": "QCB + Punch",
		"Startup": "10",
		"Hit": "6",
		"Recovery": "1",
		"Block Advantage": "13",
		"Cancel": {
      "?": false,
      "??": false,
			"Super Art": false,
			"Special": true,
			"Self": false,
			"Normal/Chain": false,
			"Dash": false,
			"Superjump": false
		},
		"Parry": "H+L",
		"Throw Range": "-",
		"Damage": "21",
		"Stun": "0",
		"Meter Gain Opponent": "0"
	},
	"Zenpou Tenshin": {
		"Motion": "HCB + Kick",
		"Startup": "5",
		"Hit": "2",
		"Recovery": "26",
		"Block Advantage": "0",
		"Cancel": {
      "?": false,
      "??": false,
			"Super Art": false,
			"Special": false,
			"Self": false,
			"Normal/Chain": false,
			"Dash": false,
			"Superjump": false
		},
		"Parry": "-",
		"Throw Range": "12",
		"Damage": "-",
		"Stun": "-",
		"Meter Gain Opponent": "0"
  }
}