{
	"Name": "Remy / レミー",
	"Category": "Normals",
	"Jab": {
		"Startup": "4",
		"Hit": "4",
		"Recovery": "4",
		"Blk. Adv.": "3",
		"Hit Adv.": "3",
		"Cr. Hit Adv.": "3",
		"Cancel": {
      "?": false,
      "??": true,
			"Super Art": true,
			"Special": true,
			"Self": false,
			"Normal/Chain": false,
			"Dash": false,
			"Superjump": false
		},
		"Parry": "H L",
		"Kara Range": "0",
		"Throw Range": "-",
		"Damage": "5",
		"Stun": "3",
		"Meter Gain Player": "0 / 2 / 1",
		"Meter Gain Opp.": "0 / 0"
	},
	"Strong": {
		"Startup": "5",
		"Hit": "5",
		"Recovery": "8",
		"Blk. Adv.": "5",
		"Hit Adv.": "6",
		"Cr. Hit Adv.": "7",
		"Cancel": {
      "?": false,
      "??": false,
			"Super Art": true,
			"Special": true,
			"Self": false,
			"Normal/Chain": false,
			"Dash": false,
			"Superjump": false
		},
		"Parry": "H",
		"Kara Range": "14",
		"Throw Range": "-",
		"Damage": "12",
		"Stun": "7",
		"Meter Gain Player": "2 / 11 / 6",
		"Meter Gain Opp.": "2 / 0"
	},
	"Fierce": {
		"Startup": "6",
		"Hit": "7",
		"Recovery": "8",
		"Blk. Adv.": "1",
		"Hit Adv.": "3",
		"Cr. Hit Adv.": "5",
		"Cancel": {
      "?": false,
      "??": false,
			"Super Art": true,
			"Special": true,
			"Self": false,
			"Normal/Chain": false,
			"Dash": false,
			"Superjump": false
		},
		"Parry": "H",
		"Kara Range": "0",
		"Throw Range": "-",
		"Damage": "21",
		"Stun": "9",
		"Meter Gain Player": "3 / 19 / 10",
		"Meter Gain Opp.": "4 / 0"
	},
	"Far Jab": {
		"Startup": "4",
		"Hit": "4",
		"Recovery": "3",
		"Blk. Adv.": "4",
		"Hit Adv.": "4",
		"Cr. Hit Adv.": "4",
		"Cancel": {
      "?": false,
      "??": true,
			"Super Art": false,
			"Special": false,
			"Self": true,
			"Normal/Chain": false,
			"Dash": false,
			"Superjump": false
		},
		"Parry": "H L",
		"Kara Range": "1",
		"Throw Range": "-",
		"Damage": "3",
		"Stun": "3",
		"Meter Gain Player": "0 / 2 / 1",
		"Meter Gain Opp.": "0 / 0"
	},
	"Far Strong": {
		"Startup": "7",
		"Hit": "3",
		"Recovery": "12",
		"Blk. Adv.": "1",
		"Hit Adv.": "2",
		"Cr. Hit Adv.": "3",
		"Cancel": {
      "?": false,
      "??": false,
			"Super Art": false,
			"Special": false,
			"Self": false,
			"Normal/Chain": false,
			"Dash": false,
			"Superjump": false
		},
		"Parry": "H",
		"Kara Range": "21",
		"Throw Range": "-",
		"Damage": "10",
		"Stun": "9",
		"Meter Gain Player": "2 / 11 / 6",
		"Meter Gain Opp.": "2 / 0"
	},
	"Far Fierce": {
		"Startup": "10",
		"Hit": "5",
		"Recovery": "18",
		"Blk. Adv.": "-2",
		"Hit Adv.": "0",
		"Cr. Hit Adv.": "2",
		"Cancel": {
      "?": false,
      "??": false,
			"Super Art": false,
			"Special": false,
			"Self": false,
			"Normal/Chain": false,
			"Dash": false,
			"Superjump": false
		},
		"Parry": "H",
		"Kara Range": "9",
		"Throw Range": "-",
		"Damage": "19",
		"Stun": "7",
		"Meter Gain Player": "3 / 19 / 10",
		"Meter Gain Opp.": "4 / 0"
	},
	"Crouching Jab": {
		"Startup": "5",
		"Hit": "2",
		"Recovery": "7",
		"Blk. Adv.": "2",
		"Hit Adv.": "2",
		"Cr. Hit Adv.": "2",
		"Cancel": {
      "?": false,
      "??": true,
			"Super Art": true,
			"Special": true,
			"Self": true,
			"Normal/Chain": false,
			"Dash": false,
			"Superjump": false
		},
		"Parry": "H L",
		"Kara Range": "0",
		"Throw Range": "-",
		"Damage": "3",
		"Stun": "3",
		"Meter Gain Player": "0 / 2 / 1",
		"Meter Gain Opp.": "0 / 0"
	},
	"Crouching Strong": {
		"Startup": "5",
		"Hit": "5",
		"Recovery": "11",
		"Blk. Adv.": "-2",
		"Hit Adv.": "-1",
		"Cr. Hit Adv.": "0",
		"Cancel": {
      "?": false,
      "??": false,
			"Super Art": true,
			"Special": true,
			"Self": false,
			"Normal/Chain": false,
			"Dash": false,
			"Superjump": false
		},
		"Parry": "H L",
		"Kara Range": "0",
		"Throw Range": "-",
		"Damage": "9",
		"Stun": "5",
		"Meter Gain Player": "2 / 11 / 6",
		"Meter Gain Opp.": "2 / 0"
	},
	"Crouching Fierce": {
		"Startup": "8",
		"Hit": "6",
		"Recovery": "18",
		"Blk. Adv.": "-5",
		"Hit Adv.": "D",
		"Cr. Hit Adv.": "D",
		"Cancel": {
      "?": false,
      "??": false,
			"Super Art": false,
			"Special": false,
			"Self": false,
			"Normal/Chain": false,
			"Dash": false,
			"Superjump": false
		},
		"Parry": "H L",
		"Kara Range": "6",
		"Throw Range": "-",
		"Damage": "17",
		"Stun": "9",
		"Meter Gain Player": "3 / 19 / 10",
		"Meter Gain Opp.": "4 / 0"
	},
	"Jumping Jab": {
		"Startup": "4",
		"Hit": "20",
		"Recovery": "-",
		"Blk. Adv.": "-",
		"Hit Adv.": "-",
		"Cr. Hit Adv.": "-",
		"Cancel": {
      "?": false,
      "??": false,
			"Super Art": false,
			"Special": false,
			"Self": false,
			"Normal/Chain": false,
			"Dash": false,
			"Superjump": false
		},
		"Parry": "H",
		"Kara Range": "0",
		"Throw Range": "-",
		"Damage": "7",
		"Stun": "7",
		"Meter Gain Player": "0 / 2 / 1",
		"Meter Gain Opp.": "0 / 0"
	},
	"Jumping Strong": {
		"Startup": "5",
		"Hit": "14",
		"Recovery": "-",
		"Blk. Adv.": "-",
		"Hit Adv.": "-",
		"Cr. Hit Adv.": "-",
		"Cancel": {
      "?": false,
      "??": false,
			"Super Art": false,
			"Special": false,
			"Self": false,
			"Normal/Chain": false,
			"Dash": false,
			"Superjump": false
		},
		"Parry": "H",
		"Kara Range": "0",
		"Throw Range": "-",
		"Damage": "12",
		"Stun": "11",
		"Meter Gain Player": "2 / 11 / 6",
		"Meter Gain Opp.": "2 / 0"
	},
	"Jumping Fierce": {
		"Startup": "9",
		"Hit": "5",
		"Recovery": "-",
		"Blk. Adv.": "-",
		"Hit Adv.": "-",
		"Cr. Hit Adv.": "-",
		"Cancel": {
      "?": false,
      "??": false,
			"Super Art": false,
			"Special": false,
			"Self": false,
			"Normal/Chain": false,
			"Dash": false,
			"Superjump": false
		},
		"Parry": "H",
		"Kara Range": "0",
		"Throw Range": "-",
		"Damage": "22",
		"Stun": "15",
		"Meter Gain Player": "3 / 19 / 10",
		"Meter Gain Opp.": "4 / 0"
	},
	"Short": {
		"Startup": "2",
		"Hit": "5",
		"Recovery": "7",
		"Blk. Adv.": "0",
		"Hit Adv.": "0",
		"Cr. Hit Adv.": "0",
		"Cancel": {
      "?": false,
      "??": false,
			"Super Art": true,
			"Special": true,
			"Self": false,
			"Normal/Chain": false,
			"Dash": false,
			"Superjump": false
		},
		"Parry": "H L",
		"Kara Range": "12",
		"Throw Range": "-",
		"Damage": "6",
		"Stun": "5",
		"Meter Gain Player": "0 / 2 / 1",
		"Meter Gain Opp.": "0 / 0"
	},
	"Forward": {
		"Startup": "4",
		"Hit": "6",
		"Recovery": "11",
		"Blk. Adv.": "1",
		"Hit Adv.": "3",
		"Cr. Hit Adv.": "5",
		"Cancel": {
      "?": false,
      "??": true,
			"Super Art": true,
			"Special": true,
			"Self": false,
			"Normal/Chain": false,
			"Dash": false,
			"Superjump": false
		},
		"Parry": "H",
		"Kara Range": "12",
		"Throw Range": "-",
		"Damage": "16",
		"Stun": "9",
		"Meter Gain Player": "2 / 11 / 6",
		"Meter Gain Opp.": "2 / 0"
	},
	"Roundhouse": {
		"Startup": "7",
		"Hit": "7",
		"Recovery": "13",
		"Blk. Adv.": "3",
		"Hit Adv.": "5",
		"Cr. Hit Adv.": "7",
		"Cancel": {
      "?": false,
      "??": false,
			"Super Art": true,
			"Special": true,
			"Self": false,
			"Normal/Chain": false,
			"Dash": false,
			"Superjump": false
		},
		"Parry": "H",
		"Kara Range": "-3",
		"Throw Range": "-",
		"Damage": "23",
		"Stun": "15",
		"Meter Gain Player": "3 / 25 / 12",
		"Meter Gain Opp.": "6 / 0"
	},
	"Far Short": {
		"Startup": "2",
		"Hit": "5",
		"Recovery": "4",
		"Blk. Adv.": "2",
		"Hit Adv.": "2",
		"Cr. Hit Adv.": "2",
		"Cancel": {
      "?": false,
      "??": false,
			"Super Art": false,
			"Special": false,
			"Self": false,
			"Normal/Chain": false,
			"Dash": false,
			"Superjump": false
		},
		"Parry": "H L",
		"Kara Range": "0",
		"Throw Range": "-",
		"Damage": "5",
		"Stun": "3",
		"Meter Gain Player": "0 / 2 / 1",
		"Meter Gain Opp.": "0 / 0"
	},
	"Far Forward": {
		"Startup": "8",
		"Hit": "5",
		"Recovery": "14",
		"Blk. Adv.": "-3",
		"Hit Adv.": "-2",
		"Cr. Hit Adv.": "-1",
		"Cancel": {
      "?": false,
      "??": false,
			"Super Art": false,
			"Special": false,
			"Self": false,
			"Normal/Chain": false,
			"Dash": false,
			"Superjump": false
		},
		"Parry": "H",
		"Kara Range": "0",
		"Throw Range": "-",
		"Damage": "14",
		"Stun": "7",
		"Meter Gain Player": "2 / 11 / 6",
		"Meter Gain Opp.": "2 / 0"
	},
	"Far Roundhouse": {
		"Startup": "10",
		"Hit": "3",
		"Recovery": "23",
		"Blk. Adv.": "-9",
		"Hit Adv.": "-7",
		"Cr. Hit Adv.": "-5",
		"Cancel": {
      "?": false,
      "??": false,
			"Super Art": false,
			"Special": false,
			"Self": false,
			"Normal/Chain": false,
			"Dash": false,
			"Superjump": false
		},
		"Parry": "H",
		"Kara Range": "27",
		"Throw Range": "-",
		"Damage": "23",
		"Stun": "11",
		"Meter Gain Player": "3 / 19 / 10",
		"Meter Gain Opp.": "4 / 0"
	},
	"Crouching Short": {
		"Startup": "3",
		"Hit": "4",
		"Recovery": "7",
		"Blk. Adv.": "0",
		"Hit Adv.": "0",
		"Cr. Hit Adv.": "0",
		"Cancel": {
      "?": false,
      "??": false,
			"Super Art": true,
			"Special": true,
			"Self": false,
			"Normal/Chain": false,
			"Dash": false,
			"Superjump": false
		},
		"Parry": "L",
		"Kara Range": "0",
		"Throw Range": "-",
		"Damage": "5",
		"Stun": "3",
		"Meter Gain Player": "0 / 2 / 1",
		"Meter Gain Opp.": "0 / 0"
	},
	"Crouching Forward": {
		"Startup": "8",
		"Hit": "5",
		"Recovery": "18",
		"Blk. Adv.": "-9",
		"Hit Adv.": "-8",
		"Cr. Hit Adv.": "-7",
		"Cancel": {
      "?": false,
      "??": false,
			"Super Art": false,
			"Special": false,
			"Self": false,
			"Normal/Chain": false,
			"Dash": false,
			"Superjump": false
		},
		"Parry": "L",
		"Kara Range": "8",
		"Throw Range": "-",
		"Damage": "10",
		"Stun": "3",
		"Meter Gain Player": "2 / 11 / 6",
		"Meter Gain Opp.": "2 / 0"
	},
	"Crouching Roundhouse": {
		"Startup": "9",
		"Hit": "7",
		"Recovery": "21",
		"Blk. Adv.": "-11",
		"Hit Adv.": "D",
		"Cr. Hit Adv.": "D",
		"Cancel": {
      "?": false,
      "??": false,
			"Super Art": false,
			"Special": false,
			"Self": false,
			"Normal/Chain": false,
			"Dash": false,
			"Superjump": false
		},
		"Parry": "L",
		"Kara Range": "7",
		"Throw Range": "-",
		"Damage": "17",
		"Stun": "3",
		"Meter Gain Player": "6 / 22 / 20",
		"Meter Gain Opp.": "4 / 0"
	},
	"Jumping Short": {
		"Startup": "4",
		"Hit": "14",
		"Recovery": "-",
		"Blk. Adv.": "-",
		"Hit Adv.": "-",
		"Cr. Hit Adv.": "-",
		"Cancel": {
      "?": false,
      "??": false,
			"Super Art": false,
			"Special": false,
			"Self": false,
			"Normal/Chain": false,
			"Dash": false,
			"Superjump": false
		},
		"Parry": "H",
		"Kara Range": "0",
		"Throw Range": "-",
		"Damage": "8",
		"Stun": "5",
		"Meter Gain Player": "0 / 2 / 1",
		"Meter Gain Opp.": "0 / 0"
	},
	"Jumping Forward": {
		"Startup": "6",
		"Hit": "4",
		"Recovery": "-",
		"Blk. Adv.": "-",
		"Hit Adv.": "-",
		"Cr. Hit Adv.": "-",
		"Cancel": {
      "?": false,
      "??": false,
			"Super Art": false,
			"Special": false,
			"Self": false,
			"Normal/Chain": false,
			"Dash": false,
			"Superjump": false
		},
		"Parry": "H",
		"Kara Range": "0",
		"Throw Range": "-",
		"Damage": "16",
		"Stun": "9",
		"Meter Gain Player": "2 / 11 / 6",
		"Meter Gain Opp.": "2 / 0"
	},
	"Jumping Roundhouse": {
		"Startup": "10",
		"Hit": "4",
		"Recovery": "-",
		"Blk. Adv.": "-",
		"Hit Adv.": "-",
		"Cr. Hit Adv.": "-",
		"Cancel": {
      "?": false,
      "??": false,
			"Super Art": false,
			"Special": false,
			"Self": false,
			"Normal/Chain": false,
			"Dash": false,
			"Superjump": false
		},
		"Parry": "H",
		"Kara Range": "0",
		"Throw Range": "-",
		"Damage": "21",
		"Stun": "13",
		"Meter Gain Player": "3 / 19 / 10",
		"Meter Gain Opp.": "4 / 0"
	},
	"Towards + Forward": {
		"Startup": "18",
		"Hit": "3",
		"Recovery": "20",
		"Blk. Adv.": "-7",
		"Hit Adv.": "-6",
		"Cr. Hit Adv.": "-5",
		"Cancel": {
      "?": false,
      "??": false,
			"Super Art": false,
			"Special": false,
			"Self": false,
			"Normal/Chain": false,
			"Dash": false,
			"Superjump": false
		},
		"Parry": "H",
		"Kara Range": "16",
		"Throw Range": "-",
		"Damage": "14",
		"Stun": "3",
		"Meter Gain Player": "2 / 11 / 6",
		"Meter Gain Opp.": "2 / 0"
	},
	"Neutral Throw": {
		"Startup": "2",
		"Hit": "1",
		"Recovery": "21",
		"Blk. Adv.": "0",
		"Hit Adv.": "D",
		"Cr. Hit Adv.": "D",
		"Cancel": {
      "?": false,
      "??": false,
			"Super Art": false,
			"Special": false,
			"Self": false,
			"Normal/Chain": false,
			"Dash": false,
			"Superjump": false
		},
		"Parry": "-",
		"Kara Range": "15",
		"Throw Range": "9",
		"Damage": "17",
		"Stun": "12",
		"Meter Gain Player": "0 / 7 / 0",
		"Meter Gain Opp.": "2 / 7"
	},
	"Throw": {
		"Startup": "2",
		"Hit": "1",
		"Recovery": "21",
		"Blk. Adv.": "0",
		"Hit Adv.": "D",
		"Cr. Hit Adv.": "D",
		"Cancel": {
      "?": false,
      "??": false,
			"Super Art": false,
			"Special": false,
			"Self": false,
			"Normal/Chain": false,
			"Dash": false,
			"Superjump": false
		},
		"Parry": "-",
		"Kara Range": "15",
		"Throw Range": "9",
		"Damage": "23",
		"Stun": "4",
		"Meter Gain Player": "0 / 8 / 0",
		"Meter Gain Opp.": "2 / 7"
	},
	"Universal Overhead": {
		"Startup": "15",
		"Hit": "10",
		"Recovery": "5",
		"Blk. Adv.": "-",
		"Hit Adv.": "-",
		"Cr. Hit Adv.": "-",
		"Cancel": {
      "?": false,
      "??": false,
			"Super Art": false,
			"Special": false,
			"Self": false,
			"Normal/Chain": false,
			"Dash": false,
			"Superjump": false
		},
		"Parry": "H",
		"Kara Range": "0",
		"Throw Range": "-",
		"Damage": "7",
		"Stun": "3",
		"Meter Gain Player": "0 / 2 / 1",
		"Meter Gain Opp.": "0 / 0"
	},
	"Taunt": {
		"Startup": "-",
		"Hit": "-",
		"Recovery": "131",
		"Blk. Adv.": "-",
		"Hit Adv.": "-",
		"Cr. Hit Adv.": "-",
		"Cancel": {
      "?": false,
      "??": false,
			"Super Art": false,
			"Special": false,
			"Self": false,
			"Normal/Chain": false,
			"Dash": false,
			"Superjump": false
		},
		"Parry": "-",
		"Kara Range": "-",
		"Throw Range": "-",
		"Damage": "-",
		"Stun": "-",
		"Meter Gain Player": "-",
		"Meter Gain Opp.": "-"
  }
}